<?xml version="1.0" encoding="windows-1251"?>
<Workbook xmlns="urn:schemas-microsoft-com:office:spreadsheet" xmlns:x="urn:schemas-microsoft-com:office:excel" xmlns:ss="urn:schemas-microsoft-com:office:spreadsheet" xmlns:html="http://www.w3.org/TR/REC-html40"><Styles><Style ss:ID="Default" ss:Name="Normal"><Alignment ss:Vertical="Bottom"/><Borders/><Font ss:FontName="Calibri" x:CharSet="204" x:Family="Swiss" ss:Size="11" ss:Color="#000000"/><Interior/><NumberFormat/><Protection/></Style><Style ss:ID="Header"><Alignment ss:Horizontal="Left" ss:Vertical="Center"/></Style><Style ss:ID="LeftContext"><Alignment ss:Horizontal="Right" ss:Vertical="Center"/></Style><Style ss:ID="CC"><Alignment ss:Horizontal="Left" ss:Vertical="Center"/></Style><Style ss:ID="RightContext"><Alignment ss:Horizontal="Left" ss:Vertical="Center"/></Style></Styles><Worksheet ss:Name="Результаты поиска"/></Workbook>
